taylogger/__init__.py
taylogger/middleware.py
taylogger/utils.py
django_taylogger_middleware-0.1.dist-info/LICENSE
django_taylogger_middleware-0.1.dist-info/METADATA
django_taylogger_middleware-0.1.dist-info/WHEEL
django_taylogger_middleware-0.1.dist-info/top_level.txt
django_taylogger_middleware-0.1.dist-info/RECORD
